{"cameraMode":{"drawMode":0,"name":"Shaded","section":"Shading Mode"},"sceneLighting":false,"audioPlay":false,"sceneViewState":{"m_AlwaysRefresh":false,"showFog":true,"showSkybox":true,"showFlares":true,"showImageEffects":true,"showParticleSystems":true,"showVisualEffectGraphs":true,"m_FxEnabled":true},"in2DMode":false,"pivot":{"x":92.33747100830078,"y":-8.10308837890625,"z":23.28792953491211},"rotation":{"x":-0.22189199924468995,"y":0.05649448186159134,"z":-0.012730538845062256,"w":-0.9742328524589539},"size":26.83110237121582,"orthographic":false}